{
    "fluentMethods": true,
    "relationships": [],
    "fields": [
        {
            "fieldName": "name",
            "fieldType": "String",
            "fieldValidateRules": [
                "required"
            ]
        },
        {
            "fieldName": "description",
            "fieldType": "String",
            "fieldValidateRules": [
                "required"
            ]
        },
        {
            "fieldName": "file",
            "fieldType": "byte[]",
            "fieldTypeBlobContent": "label",
            "fieldValidateRules": [
                "required"
            ]
        },
        {
            "fieldName": "xType",
            "fieldType": "XMLType",
            "fieldValues": "PATIENT,ENVIRONMENTAL",
            "fieldValidateRules": [
                "required"
            ]
        }
    ],
    "changelogDate": "20170315175434",
    "entityTableName": "xml_config",
    "dto": "no",
    "pagination": "no",
    "service": "serviceImpl"
}
